ls_r2x4/__init__.py
ls_r2x4/__main__.py
ls_r2x4/_connection.py
ls_r2x4/_utils.py
ls_r2x4/r2x4.py
ls_r2x4/demo/__init__.py
ls_r2x4/demo/demo.py
ls_r2x4/demo/demo_notebook.ipynb
ls_r2x4/gui/__init__.py
ls_r2x4/gui/gdconf.json
ls_r2x4/gui/gdesk_panel.py
ls_r2x4/gui/jupyterlab_widget.py
ls_r2x4/gui/qt_widget.py
ls_r2x4/gui/tkinter_gui.py
ls_r2x4/calib_data/ls_3821846592/calib_0.json
ls_r2x4/calib_data/ls_3821846592/calib_1.json
ls_r2x4/calib_data/ls_3821846592/calib_2.json
ls_r2x4/calib_data/ls_3821846592/calib_3.json
ls_r2x4/calib_data/ls_3821846592/tuned_voltages.json
ind_ls_r2x4-0.2.0rc1.dist-info/METADATA
ind_ls_r2x4-0.2.0rc1.dist-info/WHEEL
ind_ls_r2x4-0.2.0rc1.dist-info/entry_points.txt
ind_ls_r2x4-0.2.0rc1.dist-info/RECORD
