Metadata-Version: 2.4
Name: ind-ls-r2x4
Version: 0.2.0rc1
Summary: Interface the R2X4 light source from Industrialise.
Project-URL: Home, https://industrialise.be
Author-email: Lou Vervecken <lou.vervecken@industrialise.be>
Requires-Python: <3.14,>=3.8
Requires-Dist: cobs
Requires-Dist: pyserial~=3.5
